{
  "current_sprint": {
    "number": 1,
    "status": "completed",
    "branch": "feature/20260405-sprint-1",
    "plan_approved": true,
    "pr_number": 10
  },
  "last_completed": {
    "number": 1,
    "date": "2026-04-05",
    "result": "complete",
    "items_completed": 3,
    "items_carried_over": 0,
    "key_lesson": "Verify relative import paths in test files before running"
  },
  "test_metrics": {
    "backend_tests_passing": 70,
    "frontend_tests_passing": 29,
    "lint_errors": 0
  }
}
